bars/__init__.py
bars/domain.py
bars/repository.py
price_bars-0.0.1.dist-info/METADATA
price_bars-0.0.1.dist-info/WHEEL
price_bars-0.0.1.dist-info/top_level.txt
price_bars-0.0.1.dist-info/RECORD
